numpyai/__init__.py
numpyai/_ai.py
numpyai/_array.py
numpyai/_diagnosis.py
numpyai/_exceptions.py
numpyai/_session.py
numpyai/_utils.py
numpyai/_validator.py
numpyai-0.2.0.dist-info/licenses/LICENSE
numpyai-0.2.0.dist-info/METADATA
numpyai-0.2.0.dist-info/WHEEL
numpyai-0.2.0.dist-info/top_level.txt
numpyai-0.2.0.dist-info/RECORD
