Metadata-Version: 2.4
Name: numpyai
Version: 0.2.0
Summary: A library for extracting documentation and implementing a RAG system.
Author: Aadya Chinubhai
Author-email: aadyachinubhai@gmail.com
Classifier: Programming Language :: Python :: 3
Classifier: License :: OSI Approved :: MIT License
Classifier: Operating System :: OS Independent
Requires-Python: >=3.11
License-File: LICENSE
Requires-Dist: numpy
Requires-Dist: google-generativeai
Requires-Dist: rich
Dynamic: author
Dynamic: author-email
Dynamic: classifier
Dynamic: license-file
Dynamic: requires-dist
Dynamic: requires-python
Dynamic: summary
